[
  {
    "id": "2018016098444863053",
    "href": "https://www.zhihu.com/question/2018016098444863053",
    "title": "新一代小米 SU7 发布，全系搭载 V6s Plus 超级电机，最高续航达 902km，还有哪些看点？",
    "image": "https://picx.zhimg.com/v2-48f485c67b122766ee57db3ec98a79db_400x224.png",
    "hotScore": "596 万"
  },
  {
    "id": "398758985",
    "href": "https://www.zhihu.com/question/398758985",
    "title": "有哪些你认为是「全世界都应该有的东西」，实际上只有中国才有？",
    "image": "https://pic1.zhimg.com/v2-b09cdfeb60a713b4f4757cb32875a7d4_400x224.png",
    "hotScore": "452 万"
  },
  {
    "id": "2017767643180990921",
    "href": "https://www.zhihu.com/question/2017767643180990921",
    "title": "长春警方通报路虎一分钟 8 次别停奔驰致追尾，已立为刑事案件，此前曾认定「无违法事实」，究竟怎么回事？",
    "image": "https://pic1.zhimg.com/v2-8b98c8ee1152333ffb6f40b6202beb2b_400x224.png",
    "hotScore": "337 万"
  },
  {
    "id": "2017898437954281589",
    "href": "https://www.zhihu.com/question/2017898437954281589",
    "title": "3 月 19 日沪指跌 1.39% 险守 4000 点，油气、绿电板块逆势走强，如何看待今日行情？",
    "image": "https://pic1.zhimg.com/80/v2-c4373600be6f03aacf434be55341df0a_400x224.webp?source=1def8aca",
    "hotScore": "326 万"
  },
  {
    "id": "2017932964302954834",
    "href": "https://www.zhihu.com/question/2017932964302954834",
    "title": "贾国龙创办人均 40-50 元砂锅焖面新品牌，称要承接西贝关店与员工，如何看待西贝这次「下沉自救」？",
    "image": "https://pic1.zhimg.com/80/v2-f5b677dfcf2561edfeba1dd465999f99_400x224.webp?source=1def8aca",
    "hotScore": "224 万"
  },
  {
    "id": "2017692346066630422",
    "href": "https://www.zhihu.com/question/2017692346066630422",
    "title": "美以袭击伊朗进入第 20 天，当前局势如何？还有哪些信息值得关注？",
    "image": "https://pic1.zhimg.com/80/v2-39e926b13d780c9fdaff2b71b50d819c_400x224.webp?source=1def8aca",
    "hotScore": "207 万"
  },
  {
    "id": "2017913786695186154",
    "href": "https://www.zhihu.com/question/2017913786695186154",
    "title": "5 个月增加 1 万亿美元，美国国债总额突破历史新高至 39 万亿美元，对美国经济和全球金融市场有哪些影响？",
    "image": "https://pic1.zhimg.com/80/v2-9f96186d0db0a8411afad6a9f5bf4471_400x224.webp?source=1def8aca",
    "hotScore": "190 万"
  },
  {
    "id": "2017550373682950542",
    "href": "https://www.zhihu.com/question/2017550373682950542",
    "title": "如何看待主播「芜湖大司马」直播带货宣称全网最低价，遭弹幕打脸后，厂商瞬间将该商品全网提价的操作？",
    "image": "https://picx.zhimg.com/80/v2-41dda92cc0980ee758d3bbccb5a7c036_400x224.webp?source=1def8aca",
    "hotScore": "173 万"
  },
  {
    "id": "2017879750970929531",
    "href": "https://www.zhihu.com/question/2017879750970929531",
    "title": "中国第五大城市群确定，最大特点是「散装」，长江中游凭什么跻身「第五极」？它们的核心优势是什么？",
    "image": "https://pic3.zhimg.com/50/v2-8f13570653f0d1a31417688160fa32f2_400x224.jpg",
    "hotScore": "155 万"
  },
  {
    "id": "2015732331726524442",
    "href": "https://www.zhihu.com/question/2015732331726524442",
    "title": "丰巢柜超时每半天收五毛钱，网友吐槽快递被强制深夜投柜，上班来不及取，钱应该顾客出吗？",
    "image": "https://picx.zhimg.com/v2-e372da4eefa9ff98ed73a3ee1a4cdd05_400x224.png",
    "hotScore": "146 万"
  },
  {
    "id": "2018054333028071026",
    "href": "https://www.zhihu.com/question/2018054333028071026",
    "title": "伊朗称打击行动命中美国第五舰队，造成破坏有多大？对美军有哪些影响？",
    "image": "https://picx.zhimg.com/v2-7e8ee0eb1b29633fbfc1c5102fe5c247_400x224.png",
    "hotScore": "139 万"
  },
  {
    "id": "2017713766402385101",
    "href": "https://www.zhihu.com/question/2017713766402385101",
    "title": "伊朗称将打击中东三国石油设施，全力打击美相关石油设施，冲突是否会彻底失控？油价会涨到多少？",
    "image": "https://picx.zhimg.com/80/v2-c2b80d07fe117569cd28d562ad0ca459_400x224.webp?source=1def8aca",
    "hotScore": "133 万"
  },
  {
    "id": "2017890651220436716",
    "href": "https://www.zhihu.com/question/2017890651220436716",
    "title": "女子网红店等位 3200 多号等到崩溃，黄牛囤号、倒卖频发遭消费者集体投诉，门店对此该负责任吗？",
    "image": "https://picx.zhimg.com/v2-4eb005b9bfee2d010f232d5cd9136922_400x224.png",
    "hotScore": "119 万"
  },
  {
    "id": "39279003",
    "href": "https://www.zhihu.com/question/39279003",
    "title": "在中文语境中，如何翻译 token 这个词更恰当？",
    "image": "https://picx.zhimg.com/80/v2-710bd6766da5697b033d97e4eae4e498_400x224.webp?source=1def8aca",
    "hotScore": "99 万"
  },
  {
    "id": "2017989202420180694",
    "href": "https://www.zhihu.com/question/2017989202420180694",
    "title": "外交部回应以称以军击杀任何伊官员无需批准，「对这一说法感到震惊」，如何看待以方近期「斩首行动」？",
    "image": "https://picx.zhimg.com/v2-9b200ae727b1d309f42eca3e0977add3_400x224.png",
    "hotScore": "98 万"
  },
  {
    "id": "2017618476248818673",
    "href": "https://www.zhihu.com/question/2017618476248818673",
    "title": "顾客带狗就餐被指「狗和餐盘距离太近」，店主砸碎全部餐具，你认为宠物能进入就餐区吗？携宠就餐该如何管理？",
    "image": "https://pica.zhimg.com/50/v2-e41ca6a60611237d07f70a3aa4612340_400x224.jpg",
    "hotScore": "97 万"
  },
  {
    "id": "2017644815920101341",
    "href": "https://www.zhihu.com/question/2017644815920101341",
    "title": "国自然基金申请 3 月 20 号全国截止，你的申请写好了么，有什么不同的感想？",
    "image": null,
    "hotScore": "96 万"
  },
  {
    "id": "2017904008459726912",
    "href": "https://www.zhihu.com/question/2017904008459726912",
    "title": "欧冠 1/4 决赛对阵出炉，皇马 vs 拜仁，巴萨 vs 马竞，巴黎 vs 利物浦，葡萄牙体育 vs 阿森纳，有何展望？",
    "image": "https://pic4.zhimg.com/50/v2-3a982a219a119b6620ef7a87ad1de5d9_400x224.jpg",
    "hotScore": "93 万"
  },
  {
    "id": "2009938838462686424",
    "href": "https://www.zhihu.com/question/2009938838462686424",
    "title": "光伏产业仍大面积亏损，2026 年或更艰难，其主要原因及未来出路是什么？",
    "image": "https://pic1.zhimg.com/v2-a9b4e75eab975d90ac653b3923d54413_400x224.jpg?source=57bbeac9",
    "hotScore": "82 万"
  },
  {
    "id": "2017579854455861705",
    "href": "https://www.zhihu.com/question/2017579854455861705",
    "title": "四川一院校放 6 天春假让学生去赏花去恋爱，高校有没有可能也推广春秋假？",
    "image": "https://picx.zhimg.com/v2-761e898be7b7946e297deb76ff6f56f3_400x224.jpg",
    "hotScore": "81 万"
  },
  {
    "id": "2018007778287994133",
    "href": "https://www.zhihu.com/question/2018007778287994133",
    "title": "现货黄金跌破 4600 美元 / 盎司，现货白银失守 70 美元关口，有哪些影响因素？后续行情怎么走？",
    "image": "https://pic4.zhimg.com/50/v2-f3e4058414689963b728b759537b503b_400x224.jpg",
    "hotScore": "81 万"
  },
  {
    "id": "658524414",
    "href": "https://www.zhihu.com/question/658524414",
    "title": "买辆车的费用打车一辈子都用不完，那么买车有什么意义?",
    "image": "https://pic4.zhimg.com/50/v2-9baec93780d9bac5b46eb7cca71d0f1d_400x224.jpg",
    "hotScore": "80 万"
  },
  {
    "id": "2017862792787568038",
    "href": "https://www.zhihu.com/question/2017862792787568038",
    "title": "领导突然说要提拔我当主管，月薪涨 5K，让我别声张，结果 1 个月后他离职了，新领导不认这事，怎么办？",
    "image": "https://picx.zhimg.com/v2-7d6f5c8134ab8388d2395f0dd688a787_400x224.png",
    "hotScore": "76 万"
  },
  {
    "id": "31079568",
    "href": "https://www.zhihu.com/question/31079568",
    "title": "Palantir 为什么估值那么高？",
    "image": "https://pic4.zhimg.com/50/v2-56bf26e1632358f5e3553c2e8bd7f821_400x224.jpg",
    "hotScore": "69 万"
  },
  {
    "id": "1903949169166623260",
    "href": "https://www.zhihu.com/question/1903949169166623260",
    "title": "写作基本功每天应该做什么？",
    "image": "https://pic3.zhimg.com/50/v2-3d5ee1b7c4d9065a875d936bba23024e_400x224.jpg",
    "hotScore": "65 万"
  },
  {
    "id": "661781333",
    "href": "https://www.zhihu.com/question/661781333",
    "title": "开发一款独立游戏，除去人工成本，有多少钱是必须要用的？",
    "image": "https://pica.zhimg.com/50/v2-47394f75fcb740c010f11ef16dc458ec_400x224.jpg",
    "hotScore": "64 万"
  },
  {
    "id": "633889612",
    "href": "https://www.zhihu.com/question/633889612",
    "title": "怎么评价莫兰特这个人？",
    "image": "https://pic1.zhimg.com/50/v2-f0e68b54c297f5894c0a1ad5ea26f468_400x224.jpg",
    "hotScore": "62 万"
  },
  {
    "id": "12132151159",
    "href": "https://www.zhihu.com/question/12132151159",
    "title": "我想问读书的意义，读书一定很重要吗，我现在很迷茫?",
    "image": "https://pica.zhimg.com/50/v2-32b43a3c0919f3485fc81534fc0ab994_400x224.jpg",
    "hotScore": "61 万"
  },
  {
    "id": "2000701618967040960",
    "href": "https://www.zhihu.com/question/2000701618967040960",
    "title": "以目前 2026 年的科技和世界格局，如果再迎来一次恐龙灭绝的地球撞击事件，人类社会和地球会变成什么样？",
    "image": null,
    "hotScore": "60 万"
  },
  {
    "id": "1929816342837592527",
    "href": "https://www.zhihu.com/question/1929816342837592527",
    "title": "领导为什么不敢直接开掉你，非要耍紧手段逼你走呢？",
    "image": "https://pica.zhimg.com/50/v2-21800667004ffbc77274fb299481ef94_400x224.jpg",
    "hotScore": "59 万"
  }
]